codecolor/__init__.py
codecolor/cli.py
codecolor/codecolor.py
codecolor-0.0.2.dist-info/AUTHORS.rst
codecolor-0.0.2.dist-info/LICENSE
codecolor-0.0.2.dist-info/METADATA
codecolor-0.0.2.dist-info/WHEEL
codecolor-0.0.2.dist-info/entry_points.txt
codecolor-0.0.2.dist-info/top_level.txt
codecolor-0.0.2.dist-info/RECORD
