Metadata-Version: 2.1
Name: codecolor
Version: 0.0.2
Summary: Inspect python object code with colorful syntax highlighting
Home-page: https://github.com/zkneupper/codecolor
Author: Zachary Jonathan Kneupper
Author-email: zachary.kneupper@gmail.com
License: Apache Software License 2.0
Keywords: codecolor
Platform: UNKNOWN
Classifier: Development Status :: 2 - Pre-Alpha
Classifier: Intended Audience :: Developers
Classifier: License :: OSI Approved :: Apache Software License
Classifier: Natural Language :: English
Classifier: Programming Language :: Python :: 3
Classifier: Programming Language :: Python :: 3.5
Classifier: Programming Language :: Python :: 3.6
Classifier: Programming Language :: Python :: 3.7
Classifier: Programming Language :: Python :: 3.8
Requires-Python: >=3.5
Requires-Dist: Click (>=7.0)
